LICENSE
MANIFEST.in
README.md
requirements.txt
setup.py
ppsim/__init__.py
ppsim/__version__.py
ppsim/crn.py
ppsim/simulation.py
ppsim/simulator.c
ppsim/simulator.pyx
ppsim/snapshot.py
ppsimtest.egg-info/PKG-INFO
ppsimtest.egg-info/SOURCES.txt
ppsimtest.egg-info/dependency_links.txt
ppsimtest.egg-info/requires.txt
ppsimtest.egg-info/top_level.txt