Metadata-Version: 2.1
Name: ppsimtest
Version: 0.1.6
Summary: A package for simulating population protocols.
Home-page: https://github.com/UC-Davis-molecular-computing/ppsim
Author: Eric Severson and David Doty
License: UNKNOWN
Platform: UNKNOWN
Requires-Python: >=3.7
License-File: LICENSE
